seven_cloudapp_ndjyfs/__init__.py
seven_cloudapp_ndjyfs/route.py
seven_cloudapp_ndjyfs/handlers/__init__.py
seven_cloudapp_ndjyfs/handlers/client/__init__.py
seven_cloudapp_ndjyfs/handlers/client/act.py
seven_cloudapp_ndjyfs/handlers/client/lottery.py
seven_cloudapp_ndjyfs/handlers/client/prize.py
seven_cloudapp_ndjyfs/handlers/client/task.py
seven_cloudapp_ndjyfs/handlers/client/user.py
seven_cloudapp_ndjyfs/handlers/server/__init__.py
seven_cloudapp_ndjyfs/handlers/server/act_s.py
seven_cloudapp_ndjyfs/handlers/server/base_s.py
seven_cloudapp_ndjyfs/handlers/server/ip_s.py
seven_cloudapp_ndjyfs/handlers/server/machine_s.py
seven_cloudapp_ndjyfs/handlers/server/order_s.py
seven_cloudapp_ndjyfs/handlers/server/prize_s.py
seven_cloudapp_ndjyfs/handlers/server/report_s.py
seven_cloudapp_ndjyfs/handlers/server/user_s.py
seven_cloudapp_ndjyfs/models/__init__.py
seven_cloudapp_ndjyfs/models/business_base_model.py
seven_cloudapp_ndjyfs/models/enum.py
seven_cloudapp_ndjyfs/models/db_models/__init__.py
seven_cloudapp_ndjyfs/models/db_models/act/__init__.py
seven_cloudapp_ndjyfs/models/db_models/act/act_info_ex_model.py
seven_cloudapp_ndjyfs/models/db_models/act/act_module_ex_model.py
seven_cloudapp_ndjyfs/models/db_models/act/act_prize_ex_model.py
seven_cloudapp_ndjyfs/models/db_models/act/act_prize_senior_config_model.py
seven_cloudapp_ndjyfs/models/db_models/act/act_prize_sku_model.py
seven_cloudapp_ndjyfs/models/db_models/lottery/__init__.py
seven_cloudapp_ndjyfs/models/db_models/lottery/lottery_log_model.py
seven_cloudapp_ndjyfs/models/db_models/prize/__init__.py
seven_cloudapp_ndjyfs/models/db_models/prize/prize_roster_ex_model.py
seven_cloudapp_ndjyfs/models/db_models/user/__init__.py
seven_cloudapp_ndjyfs/models/db_models/user/user_info_ex_model.py
seven_cloudapp_ndjyfs-1.0.1.9.dist-info/LICENSE
seven_cloudapp_ndjyfs-1.0.1.9.dist-info/METADATA
seven_cloudapp_ndjyfs-1.0.1.9.dist-info/WHEEL
seven_cloudapp_ndjyfs-1.0.1.9.dist-info/top_level.txt
seven_cloudapp_ndjyfs-1.0.1.9.dist-info/RECORD
