Metadata-Version: 2.1
Name: seven-cloudapp-ndjyfs
Version: 1.0.1.9
Summary: seven_cloudapp_ndjyfs
Home-page: http://gitlab.tdtech.gao7.com/TaoBaoCloud/seven_cloudapp_ndjyfs.git
Author: seven
Author-email: tech@gao7.com
License: MIT
Platform: UNKNOWN
Classifier: Topic :: Software Development :: Libraries :: Python Modules
Classifier: Programming Language :: Python
Classifier: Programming Language :: Python :: 3.4
Classifier: Programming Language :: Python :: 3.5
Classifier: Programming Language :: Python :: 3.5
Classifier: Programming Language :: Python :: 3.6
Classifier: Programming Language :: Python :: 3.7
Classifier: Programming Language :: Python :: 3.8
Classifier: Programming Language :: Python :: 3.9
Requires-Python: ~=3.4
Requires-Dist: seven-cloudapp-frame (>=1.0.11.117)
